{
    "id": "OSSA-20250201-9221",
    "version": "1.0.0",
    "severity": "High",
    "description": "Git merge driver for ChangeLog files",
    "title": "Advisory for git-merge-changelog",
    "package_name": "git-merge-changelog",
    "publisher": "Generated by OSSA Collector",
    "last_updated": "2025-02-01T21:23:17.177001",
    "approvals": [
        {
            "consumption": true,
            "externalization": true
        }
    ],
    "purls": [
        "pkg:rpm/amzn/git-merge-changelog@0"
    ],
    "regex": [
        "^pkg:rpm/amzn/git-merge-changelog.*"
    ],
    "affected_versions": [
        "*.*",
        "0"
    ],
    "artifacts": [
        {
            "url": "file://gnulib-9f48fb9.tar.gz",
            "hashes": {
                "sha1": "1e30a75c728ac964852fdc26a35d4dacf363998c",
                "sha256": "81464773c4f5610a570fa1f48195a30328cbd04ad35368bde5bfde631c875204",
                "ssdeep": "196608:BPrvEfvA/3yg4mjN+oWe7Znjwszm7+vAEQyUBC9QpP:Vrsw/C5mp+e7Zj9zmiIEI6Ql",
                "swhid": "swh:1:cnt:1e30a75c728ac964852fdc26a35d4dacf363998c"
            },
            "swhid": "swh:1:dir:ce57bd338896127738406d46ef1c06accb93a126"
        }
    ],
    "licenses": "GPLv2+",
    "aliases": [],
    "references": "https://www.gnu.org/software/gnulib"
}