{
    "id": "OSSA-20250131-6506",
    "version": "1.0.0",
    "severity": "Informational",
    "description": "stress test a containerd daemon",
    "title": "Advisory for containerd-stress",
    "package_name": "containerd-stress",
    "publisher": "Generated by OSSA Collector",
    "last_updated": "2025-01-31T21:32:52.553808",
    "approvals": [
        {
            "consumption": true,
            "externalization": true
        }
    ],
    "purls": [
        "pkg:rpm/amzn/containerd-stress@1.7.25"
    ],
    "regex": [
        "^pkg:rpm/amzn/containerd-stress.*"
    ],
    "affected_versions": [
        "*.*",
        "1.7.25"
    ],
    "artifacts": [
        {
            "url": "file://containerd-1.7.25.tar.gz",
            "hashes": {
                "sha1": "6ab4f2743ce0283588f663eb7de0b38f461e2467",
                "sha256": "c5ad471e0b17927de6d8b1ac5252e6e63c62410a445737745eaf2f9b62f21bcf",
                "ssdeep": "196608:dx1Wx645/fkVgyI1HTUFlwPHYYku4sl3RrvFkOrKKxN5MTxCCtbByP:7U5/8ZI1HoFOHntkOrKK35KxFbY",
                "swhid": "swh:1:cnt:6ab4f2743ce0283588f663eb7de0b38f461e2467"
            },
            "swhid": "swh:1:dir:f4c87229426959bd57b722d250447b584eb5baba"
        }
    ],
    "licenses": "ASL 2.0",
    "aliases": [],
    "references": "NOASSERTION"
}