{
    "id": "OSSA-20250131-9848",
    "version": "1.0.0",
    "severity": "High",
    "description": "A perl module for simple terminal control",
    "title": "Advisory for perl-TermReadKey",
    "package_name": "perl-TermReadKey",
    "publisher": "Generated by OSSA Collector",
    "last_updated": "2025-01-31T11:33:56.990384",
    "approvals": [
        {
            "consumption": true,
            "externalization": true
        }
    ],
    "purls": [
        "pkg:rpm/almalinux/perl-TermReadKey@2.38"
    ],
    "regex": [
        "^pkg:rpm/almalinux/perl-TermReadKey.*"
    ],
    "affected_versions": [
        "*.*",
        "2.38"
    ],
    "artifacts": [
        {
            "url": "file://TermReadKey-2.38.tar.gz",
            "hashes": {
                "sha1": "e869c13a485e6c56561c34351fd62352bdac793c",
                "sha256": "5a645878dc570ac33661581fbb090ff24ebce17d43ea53fd22e105a856a47290",
                "ssdeep": "1536:z1Byp9jJULioB07zgnFHo2aOh2SU4byAviCoxOhTZ41XtuYbCT+0tpZ:z2p9jb/7zgnOOBbviCwC69uYuft",
                "swhid": "swh:1:cnt:e869c13a485e6c56561c34351fd62352bdac793c"
            },
            "swhid": "swh:1:dir:2125e04d21645412efd901bcf838a96fb29dbd30"
        }
    ],
    "licenses": "Artistic, Copyright only, GPL+",
    "aliases": [],
    "references": "https://metacpan.org/release/TermReadKey"
}