{
    "id": "OSSA-20250131-9218",
    "version": "1.0.0",
    "severity": "High",
    "description": "SGPIO captive backplane tool",
    "title": "Advisory for sgpio",
    "package_name": "sgpio",
    "publisher": "Generated by OSSA Collector",
    "last_updated": "2025-01-31T12:30:25.285373",
    "approvals": [
        {
            "consumption": true,
            "externalization": true
        }
    ],
    "purls": [
        "pkg:rpm/almalinux/sgpio@1.2.0.10"
    ],
    "regex": [
        "^pkg:rpm/almalinux/sgpio.*"
    ],
    "affected_versions": [
        "*.*",
        "1.2.0.10"
    ],
    "artifacts": [
        {
            "url": "file://sgpio-1.2-0.10-src.tar.gz",
            "hashes": {
                "sha1": "dc5f0343a3e54ca91a97ecc100011196a0a7cfb7",
                "sha256": "9bf8c42acaa247efd9321bdb1fc2390022f0c554d77fbbd4a7363d990fc0270b",
                "ssdeep": "768:0MEHKcW4PwkspYqB+g7tCTdal18bAMB4G2EW:0MkPfspYNR7lBW",
                "swhid": "swh:1:cnt:dc5f0343a3e54ca91a97ecc100011196a0a7cfb7"
            },
            "swhid": "swh:1:dir:2c503df897d5f2f82094717937f9f002ef11585c"
        }
    ],
    "licenses": "GPLv2+",
    "aliases": [],
    "references": "http://sources.redhat.com/lvm2/wiki/DMRAID_Eventing"
}