{
    "id": "OSSA-20250131-6943",
    "version": "1.0.0",
    "severity": "High",
    "description": ".NET command line host resolver",
    "title": "Advisory for dotnet-hostfxr-6.0",
    "package_name": "dotnet-hostfxr-6.0",
    "publisher": "Generated by OSSA Collector",
    "last_updated": "2025-01-31T05:05:12.260255",
    "approvals": [
        {
            "consumption": true,
            "externalization": true
        }
    ],
    "purls": [
        "pkg:rpm/almalinux/dotnet-hostfxr-6.0@6.0.35"
    ],
    "regex": [
        "^pkg:rpm/almalinux/dotnet-hostfxr-6.0.*"
    ],
    "affected_versions": [
        "*.*",
        "6.0.35"
    ],
    "artifacts": [
        {
            "url": "file://dotnet-v6.0.135.tar.gz",
            "hashes": {
                "sha1": "2afbea98a8b143f8605fcd1839160ffb3b8401eb",
                "sha256": "645ba51c7e8ebb750a58d4031acfda6d25958b33af2855c7c82ede856ae801f4",
                "ssdeep": "12582912:Rir/PQ8aFOpJIqCL1TOUOy9uebcOtVwcb69jLeiHoxkfLl:+Q5FkJZuTueRVOeHkfLl",
                "swhid": "swh:1:cnt:2afbea98a8b143f8605fcd1839160ffb3b8401eb"
            },
            "swhid": "swh:1:dir:db799b3c808163aba246bee2a736f92d628219dc"
        }
    ],
    "licenses": "ASL 2.0, BSD, CC-BY, CC0, EPL-1.0, GPL+, GPLv2, ISC, LGPLv2+, MIT, MS-PL, OFL, zlib",
    "aliases": [],
    "references": "https://github.com/dotnet/"
}