{
    "id": "OSSA-20250131-2027",
    "version": "1.0.0",
    "severity": "High",
    "description": "LAME MP3 encoding library",
    "title": "Advisory for lame-libs",
    "package_name": "lame-libs",
    "publisher": "Generated by OSSA Collector",
    "last_updated": "2025-01-31T08:41:32.197537",
    "approvals": [
        {
            "consumption": true,
            "externalization": true
        }
    ],
    "purls": [
        "pkg:rpm/almalinux/lame-libs@3.100"
    ],
    "regex": [
        "^pkg:rpm/almalinux/lame-libs.*"
    ],
    "affected_versions": [
        "*.*",
        "3.100"
    ],
    "artifacts": [
        {
            "url": "file://lame-3.100.tar.gz",
            "hashes": {
                "sha1": "64c53b1a4d493237cef5e74944912cd9f98e618d",
                "sha256": "ddfe36cab873794038ae2c1210557ad34857a4b6bdc515785d1da9e175b1da1e",
                "ssdeep": "24576:fmUyi2S8UtYrBlUk2vGMq0oSQpuRzoyHSrFnbZxgdsOMcRk3fDtm5khogXMk7+4p:fmUyiz8DD2vGMq5wzogSrlkdbcpCgXlf",
                "swhid": "swh:1:cnt:64c53b1a4d493237cef5e74944912cd9f98e618d"
            },
            "swhid": "swh:1:dir:a496da0c9c30242609cdaa6fc2425563697b9d8f"
        }
    ],
    "licenses": "GPLv2+",
    "aliases": [],
    "references": "http://lame.sourceforge.net/"
}