{
    "id": "OSSA-20250131-9558",
    "version": "1.0.0",
    "severity": "High",
    "description": "Utilities for monitoring process activities",
    "title": "Advisory for psacct",
    "package_name": "psacct",
    "publisher": "Generated by OSSA Collector",
    "last_updated": "2025-01-31T11:48:32.686988",
    "approvals": [
        {
            "consumption": true,
            "externalization": true
        }
    ],
    "purls": [
        "pkg:rpm/almalinux/psacct@6.6.4"
    ],
    "regex": [
        "^pkg:rpm/almalinux/psacct.*"
    ],
    "affected_versions": [
        "*.*",
        "6.6.4"
    ],
    "artifacts": [
        {
            "url": "file://acct-6.6.4.tar.gz",
            "hashes": {
                "sha1": "bf4bb9c138d325add34a8cd836e44a49bc64dfe9",
                "sha256": "4c15bf2b58b16378bcc83f70e77d4d40ab0b194acf2ebeefdb507f151faa663f",
                "ssdeep": "24576:5Lw9wXiTXPHgHZITPVuRvcudd8HYWJK49sQOw53h1:5LSwyzPHSZITPVuRHdSHzs49T",
                "swhid": "swh:1:cnt:bf4bb9c138d325add34a8cd836e44a49bc64dfe9"
            },
            "swhid": "swh:1:dir:4d3a61ee01da5a163d242ad271efb906c927d9bf"
        }
    ],
    "licenses": "GPLv3+",
    "aliases": [],
    "references": "http://www.gnu.org/software/acct/"
}