{
    "id": "OSSA-20250131-6277",
    "version": "1.0.0",
    "severity": "Informational",
    "description": "Lark is a modern general-purpose parsing library for Python",
    "title": "Advisory for python3-lark-parser",
    "package_name": "python3-lark-parser",
    "publisher": "Generated by OSSA Collector",
    "last_updated": "2025-01-31T11:51:51.255161",
    "approvals": [
        {
            "consumption": true,
            "externalization": true
        }
    ],
    "purls": [
        "pkg:rpm/almalinux/python3-lark-parser@0.9.0"
    ],
    "regex": [
        "^pkg:rpm/almalinux/python3-lark-parser.*"
    ],
    "affected_versions": [
        "*.*",
        "0.9.0"
    ],
    "artifacts": [],
    "licenses": "MIT",
    "aliases": [],
    "references": "https://github.com/lark-parser/lark"
}