{
    "id": "OSSA-20250131-1791",
    "version": "1.0.0",
    "severity": "Medium",
    "description": "Plugins for the Grilo framework",
    "title": "Advisory for grilo-plugins",
    "package_name": "grilo-plugins",
    "publisher": "Generated by OSSA Collector",
    "last_updated": "2025-01-31T07:28:33.434180",
    "approvals": [
        {
            "consumption": true,
            "externalization": true
        }
    ],
    "purls": [
        "pkg:rpm/almalinux/grilo-plugins@0.3.13"
    ],
    "regex": [
        "^pkg:rpm/almalinux/grilo-plugins.*"
    ],
    "affected_versions": [
        "*.*",
        "0.3.13"
    ],
    "artifacts": [
        {
            "url": "file://grilo-plugins-0.3.13.tar.xz",
            "hashes": {
                "sha1": "3a72898ff7a2d9206daf302dc78ea68c2ece15aa",
                "sha256": "1c4305d67364a930543836cc1982f30e946973b8ff6af3efe31d87709ab520f8",
                "ssdeep": "49152:0ypP/i/wTA2yMct4eMiAUeCVKQa5TzLG+Bxv:bpPaIOMXiWzLjxv",
                "swhid": "swh:1:cnt:3a72898ff7a2d9206daf302dc78ea68c2ece15aa"
            },
            "swhid": "swh:1:dir:deb9c3c2d7cae95db69026c573a5543603aa900c"
        }
    ],
    "licenses": "LGPLv2+",
    "aliases": [],
    "references": "https://wiki.gnome.org/Projects/Grilo"
}