{
    "id": "OSSA-20250131-3034",
    "version": "1.0.0",
    "severity": "Informational",
    "description": "XML Schema Object Model",
    "title": "Advisory for jaxb-xsom",
    "package_name": "jaxb-xsom",
    "publisher": "Generated by OSSA Collector",
    "last_updated": "2025-01-31T08:00:39.424819",
    "approvals": [
        {
            "consumption": true,
            "externalization": true
        }
    ],
    "purls": [
        "pkg:rpm/almalinux/jaxb-xsom@4.0.2"
    ],
    "regex": [
        "^pkg:rpm/almalinux/jaxb-xsom.*"
    ],
    "affected_versions": [
        "*.*",
        "4.0.2"
    ],
    "artifacts": [
        {
            "url": "file://jaxb-4.0.2.tar.gz",
            "hashes": {
                "sha1": "3bf3515784e9f84a71fed962b08b5f57942c7e5a",
                "sha256": "c7a53b8168894d6afac3ec6b920fa13ba7300f40de586e6e9a25decf265b12d7",
                "ssdeep": "49152:JxmO59gVwIPNsdc8k1XdNOfzAFbzodbkUVELwJNoPRF9:JcKuVXlsdcVXTOAMhkU6LwWRF9",
                "swhid": "swh:1:cnt:3bf3515784e9f84a71fed962b08b5f57942c7e5a"
            },
            "swhid": "swh:1:dir:69ef6415da0d65fb163120ca40a49548dfdbd21b"
        }
    ],
    "licenses": "BSD",
    "aliases": [],
    "references": "https://github.com/eclipse-ee4j/jaxb-ri"
}