{
    "id": "OSSA-20250131-4132",
    "version": "1.0.0",
    "severity": "Informational",
    "description": "Free Telugu font",
    "title": "Advisory for lohit-telugu-fonts",
    "package_name": "lohit-telugu-fonts",
    "publisher": "Generated by OSSA Collector",
    "last_updated": "2025-01-31T10:54:52.613260",
    "approvals": [
        {
            "consumption": true,
            "externalization": true
        }
    ],
    "purls": [
        "pkg:rpm/almalinux/lohit-telugu-fonts@2.5.5"
    ],
    "regex": [
        "^pkg:rpm/almalinux/lohit-telugu-fonts.*"
    ],
    "affected_versions": [
        "*.*",
        "2.5.5"
    ],
    "artifacts": [
        {
            "url": "file://lohit-telugu-2.5.5.tar.gz",
            "hashes": {
                "sha1": "ab0b068caab3ca36e0057086397d6a65c5e79459",
                "sha256": "fddaf9e21d198d5faeaf4f0c3bfd4070d28140243fd229af5b581119f4e11d39",
                "ssdeep": "12288:byn5OCTYXZxHYLGda2Di9g7oxc4b9q3iVz:1GYXZxHYLvXg7oa4b9qa",
                "swhid": "swh:1:cnt:ab0b068caab3ca36e0057086397d6a65c5e79459"
            },
            "swhid": "swh:1:dir:473c27ddbeb031efcf6f2fd322a923970fdfd3ff"
        }
    ],
    "licenses": "OFL",
    "aliases": [],
    "references": "https://pagure.io/lohit"
}