{
    "id": "OSSA-20250131-7628",
    "version": "1.0.0",
    "severity": "High",
    "description": "The error messages files required by server and embedded",
    "title": "Advisory for mariadb-errmsg",
    "package_name": "mariadb-errmsg",
    "publisher": "Generated by OSSA Collector",
    "last_updated": "2025-01-31T10:57:54.490059",
    "approvals": [
        {
            "consumption": true,
            "externalization": true
        }
    ],
    "purls": [
        "pkg:rpm/almalinux/mariadb-errmsg@10.5.22"
    ],
    "regex": [
        "^pkg:rpm/almalinux/mariadb-errmsg.*"
    ],
    "affected_versions": [
        "*.*",
        "10.5.22"
    ],
    "artifacts": [
        {
            "url": "file://inih-r49.tar.gz",
            "hashes": {
                "sha1": "97b3736e9aee21d2cc78383f933530d2e0716d33",
                "sha256": "197133c37a5fce2a3ac13008883b13f3a6f349881b66024c38ee9abf45e20d0c",
                "ssdeep": "384:m/MBqujlCxPYd+IENibyMCEiFwmB3uokA8W8hQM8DFdmKt:OntYdeNixJ4BkDW8hQMEKKt",
                "swhid": "swh:1:cnt:97b3736e9aee21d2cc78383f933530d2e0716d33"
            },
            "swhid": "swh:1:dir:acdbb7c652e37a53657079ab1ad913dd7f467a4a"
        }
    ],
    "licenses": "GPLv2, LGPLv2",
    "aliases": [],
    "references": "http://mariadb.org"
}