{
    "id": "OSSA-20250131-7505",
    "version": "1.0.0",
    "severity": "High",
    "description": "Albanian hunspell dictionaries",
    "title": "Advisory for hunspell-sq",
    "package_name": "hunspell-sq",
    "publisher": "Generated by OSSA Collector",
    "last_updated": "2025-01-31T07:38:51.840082",
    "approvals": [
        {
            "consumption": true,
            "externalization": true
        }
    ],
    "purls": [
        "pkg:rpm/almalinux/hunspell-sq@1.6.4"
    ],
    "regex": [
        "^pkg:rpm/almalinux/hunspell-sq.*"
    ],
    "affected_versions": [
        "*.*",
        "1.6.4"
    ],
    "artifacts": [],
    "licenses": "GPLv2+",
    "aliases": [],
    "references": "http://www.shkenca.org/k6i/albanian_dictionary_for_myspell_en.html"
}