{
    "id": "OSSA-20250131-6880",
    "version": "1.0.0",
    "severity": "High",
    "description": "Python 3 bindings for Qt5 base",
    "title": "Advisory for python3-qt5-base",
    "package_name": "python3-qt5-base",
    "publisher": "Generated by OSSA Collector",
    "last_updated": "2025-01-31T11:56:30.744722",
    "approvals": [
        {
            "consumption": true,
            "externalization": true
        }
    ],
    "purls": [
        "pkg:rpm/almalinux/python3-qt5-base@5.15.9"
    ],
    "regex": [
        "^pkg:rpm/almalinux/python3-qt5-base.*"
    ],
    "affected_versions": [
        "*.*",
        "5.15.9"
    ],
    "artifacts": [
        {
            "url": "file://PyQt5-5.15.9.tar.gz",
            "hashes": {
                "sha1": "1f68db8900204587a32eacac94e9fa5d2d204ec8",
                "sha256": "dc41e8401a90dc3e2b692b411bd5492ab559ae27a27424eed4bd3915564ec4c0",
                "ssdeep": "98304:TLvFncg+eP3Uahv8m4Nz3aw3H3ztoVP8bhuDqHd9qpstY:HFcgXcWJqza+Xzt48Nu6d93tY",
                "swhid": "swh:1:cnt:1f68db8900204587a32eacac94e9fa5d2d204ec8"
            },
            "swhid": "swh:1:dir:f60532fb94e2dc0261c4d87f1c344c217a0f5945"
        }
    ],
    "licenses": "GPLv3",
    "aliases": [],
    "references": "http://www.riverbankcomputing.com/software/pyqt/"
}