{
    "id": "OSSA-20250131-5340",
    "version": "1.0.0",
    "severity": "Medium",
    "description": "Perl bindings for libguestfs (Sys::Guestfs)",
    "title": "Advisory for perl-Sys-Guestfs",
    "package_name": "perl-Sys-Guestfs",
    "publisher": "Generated by OSSA Collector",
    "last_updated": "2025-01-31T11:33:47.097337",
    "approvals": [
        {
            "consumption": true,
            "externalization": true
        }
    ],
    "purls": [
        "pkg:rpm/almalinux/perl-Sys-Guestfs@1.50.2"
    ],
    "regex": [
        "^pkg:rpm/almalinux/perl-Sys-Guestfs.*"
    ],
    "affected_versions": [
        "*.*",
        "1.50.2"
    ],
    "artifacts": [
        {
            "url": "file://libguestfs-1.50.2.tar.gz",
            "hashes": {
                "sha1": "9a4fcb78ca452e1cf04f0b541d938ab1b07019a6",
                "sha256": "da11090bca076f17c50395971238fa994d50cf4510f7ff8448836f2f64c17923",
                "ssdeep": "393216:iVtpF3oqRMa/DQLLKz8e+dPj1OzD8bjcs+2SEEK81xroyofiMFJDF+:qtp+CMes28e+B0zoHF+tE1qoLiMXp+",
                "swhid": "swh:1:cnt:9a4fcb78ca452e1cf04f0b541d938ab1b07019a6"
            },
            "swhid": "swh:1:dir:f25479ccfad26cf327011ce37c4aa96ac9da863a"
        },
        {
            "url": "file://libguestfs-common-1.50.2.tar.gz",
            "hashes": {
                "sha1": "f801826d11e360a906bae5980495ac5425d709ae",
                "sha256": "9e86709a84c28a30a7f0601b7495522a071aea51dca2a388e4533e5a6c6d4dc7",
                "ssdeep": "3072:6iVc9kLhvI+pe6V0wC3XZyqo2oIpDlDw1KKXcDlsY86bJbLK7wC+A6TjZRzpkxfY:ZNLZtpiwoX50IZlDw0KMDlTkwC5aZRzL",
                "swhid": "swh:1:cnt:f801826d11e360a906bae5980495ac5425d709ae"
            },
            "swhid": "swh:1:dir:28a11b8942e683ba7b9c9f088ed8e4856babb5d0"
        }
    ],
    "licenses": "LGPLv2+",
    "aliases": [],
    "references": "http://libguestfs.org/"
}