{
    "id": "OSSA-20250131-2189",
    "version": "1.0.0",
    "severity": "Informational",
    "description": "Multitouch Protocol Translation Library",
    "title": "Advisory for mtdev",
    "package_name": "mtdev",
    "publisher": "Generated by OSSA Collector",
    "last_updated": "2025-01-31T11:02:31.465294",
    "approvals": [
        {
            "consumption": true,
            "externalization": true
        }
    ],
    "purls": [
        "pkg:rpm/almalinux/mtdev@1.1.5"
    ],
    "regex": [
        "^pkg:rpm/almalinux/mtdev.*"
    ],
    "affected_versions": [
        "*.*",
        "1.1.5"
    ],
    "artifacts": [],
    "licenses": "MIT",
    "aliases": [],
    "references": "http://bitmath.org/code/mtdev/"
}