{
    "id": "OSSA-20250131-4537",
    "version": "1.0.0",
    "severity": "High",
    "description": "Structured data retrieval of perl -V output",
    "title": "Advisory for perl-Config-Perl-V",
    "package_name": "perl-Config-Perl-V",
    "publisher": "Generated by OSSA Collector",
    "last_updated": "2025-01-31T11:29:20.194406",
    "approvals": [
        {
            "consumption": true,
            "externalization": true
        }
    ],
    "purls": [
        "pkg:rpm/almalinux/perl-Config-Perl-V@0.33"
    ],
    "regex": [
        "^pkg:rpm/almalinux/perl-Config-Perl-V.*"
    ],
    "affected_versions": [
        "*.*",
        "0.33"
    ],
    "artifacts": [
        {
            "url": "file://Config-Perl-V-0.33.tgz",
            "hashes": {
                "sha1": "cf1580bf994c93df5c9cc92d85f970d5b151c68c",
                "sha256": "eff679730b96ae1c6fd92151a81f2ec7b5968fb608f77472eebd6e9abb61905d",
                "ssdeep": "384:4deexTyIBd0iwnkqR+4J9DRM6fffbQqXHPbCIcrRRrj+UAFmJzSQphHFUJUYUZT:4deexTyIBuij4Lyy7deIyjj+UzJOQ3HB",
                "swhid": "swh:1:cnt:cf1580bf994c93df5c9cc92d85f970d5b151c68c"
            },
            "swhid": "swh:1:dir:19dc115895344244699614144bcbc2268737e61a"
        }
    ],
    "licenses": "Artistic, GPL+",
    "aliases": [],
    "references": "https://metacpan.org/release/Config-Perl-V"
}